subprocess4.py
subprocess4-0.1.1.dist-info/METADATA
subprocess4-0.1.1.dist-info/WHEEL
subprocess4-0.1.1.dist-info/licenses/LICENSE
subprocess4-0.1.1.dist-info/RECORD
