Metadata-Version: 2.4
Name: subprocess4
Version: 0.1.1
Summary: Python subprocess wrapper using os.wait4 to get resource usage
Project-URL: Homepage, https://github.com/JasonGross/subprocess4
Project-URL: Bug Tracker, https://github.com/JasonGross/subprocess4/issues
Author-email: Jason Gross <jgross@mit.edu>
License-File: LICENSE
Requires-Python: >=3.6
